error_helper_by_delica/__init__.py
error_helper_by_delica/error_helper_funcs.py
error_helper_by_delica-0.0.2.dist-info/licenses/LICENCE
error_helper_by_delica-0.0.2.dist-info/METADATA
error_helper_by_delica-0.0.2.dist-info/WHEEL
error_helper_by_delica-0.0.2.dist-info/top_level.txt
error_helper_by_delica-0.0.2.dist-info/RECORD
