Metadata-Version: 2.4
Name: error_helper_by_delica
Version: 0.0.2
Summary: A package for easily checking input parameters and printing informative error messages
Author: Delica Leboe-McGowan
Author-email: Delica Leboe-McGowan <stormindustries22@outlook.com>
License-Expression: MIT
Project-URL: Homepage, https://github.com/DelicaLM/error_helper_by_delica/
Classifier: Programming Language :: Python :: 3
Classifier: Operating System :: OS Independent
Requires-Python: >=3.9
License-File: LICENCE
Dynamic: author
Dynamic: license-file
